setup.py
DataDealTool/CSV_EXCEL.py
DataDealTool/__init__.py
DataDealTool/dictorder.py
DataDealTool.egg-info/PKG-INFO
DataDealTool.egg-info/SOURCES.txt
DataDealTool.egg-info/dependency_links.txt
DataDealTool.egg-info/requires.txt
DataDealTool.egg-info/top_level.txt